Metadata-Version: 2.1
Name: zrf-test-box-py
Version: 0.0.2
Summary: 短描述
Home-page: https://github.com/xxx
Author: xxx
Author-email: xxx@xxx.com
License: UNKNOWN
Platform: any
